[
  {
    "errorCodeFieldName":"errorCode",
    "correlationIdFieldName":"correlationId",
    "successFieldName":"success",
    "errorTextFieldName":"errorText",
    "name":"AxGameDemoService",
    "fullName":"com.axgrid.game.rpc.service.AxGameDemoService",
    "methods":[
      {
        "name":"pingpong",
        "requestFullName":"com.axgrid.game.rpc.OpPing",
        "requestName":"OpPing",
        "responseFullName":"com.axgrid.game.rpc.RpPing",
        "responseName":"RpPing",
        "loginRequired":false
      }
    ]
  },
  {
    "errorCodeFieldName":"errorCode",
    "correlationIdFieldName":"correlationId",
    "successFieldName":"success",
    "errorTextFieldName":"errorText",
    "name":"AxGameRPCService",
    "fullName":"com.axgrid.game.rpc.service.AxGameRPCService",
    "methods":[
      {
        "name":"ping",
        "requestFullName":"com.axgrid.game.rpc.OpPing",
        "requestName":"OpPing",
        "responseFullName":"com.axgrid.game.rpc.RpPing",
        "responseName":"RpPing",
        "loginRequired":false
      }
    ]
  }
]